python_monnify/__init__.py
python_monnify/monnify.py
python_monnify-0.3.dist-info/LICENSE
python_monnify-0.3.dist-info/METADATA
python_monnify-0.3.dist-info/WHEEL
python_monnify-0.3.dist-info/top_level.txt
python_monnify-0.3.dist-info/RECORD
